LICENSE
README.md
setup.cfg
setup.py
nettool/__init__.py
nettool/nettool.py
nettool.egg-info/PKG-INFO
nettool.egg-info/SOURCES.txt
nettool.egg-info/dependency_links.txt
nettool.egg-info/entry_points.txt
nettool.egg-info/top_level.txt