Metadata-Version: 2.1
Name: nettool
Version: 1.1
Summary: Nettool
Home-page: https://github.com/Dlunhappy226/nettool
Author: Dlunhappy226
Author-email: dlunhappy226@gmail.com
License: MIT
Download-URL: https://github.com/Dlunhappy226/nettool/archive/1.1.tar.gz
Platform: UNKNOWN
License-File: LICENSE
